{"cameraMode":{"drawMode":0,"name":"Shaded","section":"Shading Mode"},"sceneLighting":false,"audioPlay":false,"sceneViewState":{"m_AlwaysRefresh":false,"showFog":true,"showSkybox":false,"showFlares":true,"showImageEffects":true,"showParticleSystems":true,"showVisualEffectGraphs":true,"m_FxEnabled":true},"in2DMode":false,"pivot":{"x":-2.0,"y":1.2000000476837159,"z":0.0},"rotation":{"x":0.13257724046707154,"y":-0.02359035424888134,"z":0.003737078281119466,"w":0.9910467267036438},"size":1.3821523189544678,"orthographic":false}